COPYING
MANIFEST.in
README
hachoir-grep
hachoir-metadata
hachoir-strip
hachoir-subfile
hachoir-urwid
runtests.py
setup.py
doc/api.rst
doc/authors.rst
doc/changelog.rst
doc/contact.rst
doc/core.rst
doc/editor.rst
doc/grep.rst
doc/index.rst
doc/install.rst
doc/internals.rst
doc/metadata.rst
doc/metadata_examples.rst
doc/parser.rst
doc/regex.rst
doc/regex_api.rst
doc/strip.rst
doc/subfile.rst
doc/urwid.rst
hachoir/__init__.py
hachoir/grep.py
hachoir/strip.py
hachoir/test.py
hachoir/urwid_ui.py
hachoir/version.py
hachoir/core/__init__.py
hachoir/core/benchmark.py
hachoir/core/bits.py
hachoir/core/cmd_line.py
hachoir/core/config.py
hachoir/core/dict.py
hachoir/core/endian.py
hachoir/core/error.py
hachoir/core/event_handler.py
hachoir/core/i18n.py
hachoir/core/iso639.py
hachoir/core/language.py
hachoir/core/log.py
hachoir/core/memory.py
hachoir/core/profiler.py
hachoir/core/text_handler.py
hachoir/core/timeout.py
hachoir/core/tools.py
hachoir/editor/__init__.py
hachoir/editor/field.py
hachoir/editor/fieldset.py
hachoir/editor/typed_field.py
hachoir/field/__init__.py
hachoir/field/basic_field_set.py
hachoir/field/bit_field.py
hachoir/field/byte_field.py
hachoir/field/character.py
hachoir/field/enum.py
hachoir/field/fake_array.py
hachoir/field/field.py
hachoir/field/field_set.py
hachoir/field/float.py
hachoir/field/generic_field_set.py
hachoir/field/helper.py
hachoir/field/integer.py
hachoir/field/link.py
hachoir/field/new_seekable_field_set.py
hachoir/field/padding.py
hachoir/field/parser.py
hachoir/field/seekable_field_set.py
hachoir/field/static_field_set.py
hachoir/field/string_field.py
hachoir/field/sub_file.py
hachoir/field/timestamp.py
hachoir/field/vector.py
hachoir/metadata/__init__.py
hachoir/metadata/archive.py
hachoir/metadata/audio.py
hachoir/metadata/config.py
hachoir/metadata/file_system.py
hachoir/metadata/filter.py
hachoir/metadata/formatter.py
hachoir/metadata/image.py
hachoir/metadata/jpeg.py
hachoir/metadata/metadata.py
hachoir/metadata/metadata_item.py
hachoir3_superdesk.egg-info/PKG-INFO
hachoir3_superdesk.egg-info/SOURCES.txt
hachoir3_superdesk.egg-info/dependency_links.txt
hachoir3_superdesk.egg-info/top_level.txt
