Metadata-Version: 1.1
Name: hachoir3-superdesk
Version: 3.0a1.post2
Summary: Package of Hachoir parsers used to open binary files
Home-page: http://hachoir3.readthedocs.org/
Author: Hachoir team (see AUTHORS file)
Author-email: UNKNOWN
License: GNU GPL v2
Platform: UNKNOWN
Classifier: Development Status :: 5 - Production/Stable
Classifier: Environment :: Console :: Curses
Classifier: Environment :: Plugins
Classifier: Intended Audience :: Developers
Classifier: Intended Audience :: Education
Classifier: License :: OSI Approved :: GNU General Public License (GPL)
Classifier: Natural Language :: English
Classifier: Operating System :: OS Independent
Classifier: Programming Language :: Python
Classifier: Topic :: Multimedia
Classifier: Topic :: Scientific/Engineering :: Information Analysis
Classifier: Topic :: Software Development :: Disassemblers
Classifier: Topic :: Software Development :: Interpreters
Classifier: Topic :: Software Development :: Libraries :: Python Modules
Classifier: Topic :: System :: Filesystems
Classifier: Topic :: Text Processing
Classifier: Topic :: Utilities
